mmv_im2im/__init__.py
mmv_im2im/map_extractor.py
mmv_im2im/proj_tester.py
mmv_im2im/proj_trainer.py
mmv_im2im/bin/__init__.py
mmv_im2im/bin/run_im2im.py
mmv_im2im/configs/__init__.py
mmv_im2im/configs/config_base.py
mmv_im2im/configs/preset_inference_labelfree_3d.yaml
mmv_im2im/configs/preset_inference_pix2pixhd_2d.yaml
mmv_im2im/configs/preset_train_cyclegan_2d.yaml
mmv_im2im/configs/preset_train_cyclegan_3d.yaml
mmv_im2im/configs/preset_train_embedseg_2d.yaml
mmv_im2im/configs/preset_train_embedseg_3d.yaml
mmv_im2im/configs/preset_train_labelfree_2d.yaml
mmv_im2im/configs/preset_train_labelfree_3d.yaml
mmv_im2im/configs/preset_train_modality_transfer_3d.yaml
mmv_im2im/configs/preset_train_pix2pixhd_2d.yaml
mmv_im2im/configs/preset_train_pix2pixhd_3d.yaml
mmv_im2im/configs/preset_train_semanticseg_2d.yaml
mmv_im2im/configs/preset_train_semanticseg_3d.yaml
mmv_im2im/data_modules/__init__.py
mmv_im2im/data_modules/data_loader_basic.py
mmv_im2im/models/__init__.py
mmv_im2im/models/pl_FCN.py
mmv_im2im/models/pl_ProbUnet.py
mmv_im2im/models/pl_cyclegan.py
mmv_im2im/models/pl_embedseg.py
mmv_im2im/models/pl_pix2pix.py
mmv_im2im/models/nets/BranchedERFNet_2d.py
mmv_im2im/models/nets/BranchedERFNet_3d.py
mmv_im2im/models/nets/ProbUnet.py
mmv_im2im/models/nets/SA_2d.py
mmv_im2im/models/nets/__init__.py
mmv_im2im/models/nets/deeplabv3_2d.py
mmv_im2im/models/nets/erfnet.py
mmv_im2im/models/nets/erfnet_3d.py
mmv_im2im/models/nets/fnet_nn_2d.py
mmv_im2im/models/nets/fnet_nn_3d.py
mmv_im2im/models/nets/gans.py
mmv_im2im/postprocessing/__init__.py
mmv_im2im/postprocessing/basic_collection.py
mmv_im2im/postprocessing/embedseg_cluster.py
mmv_im2im/preprocessing/__init__.py
mmv_im2im/preprocessing/transforms.py
mmv_im2im/tests/__init__.py
mmv_im2im/tests/test_dummy.py
mmv_im2im/utils/__init__.py
mmv_im2im/utils/basic_losses.py
mmv_im2im/utils/connectivity_loss.py
mmv_im2im/utils/elbo_loss.py
mmv_im2im/utils/embedding_loss.py
mmv_im2im/utils/embedseg_utils.py
mmv_im2im-0.6.2.dist-info/licenses/LICENSE
mmv_im2im-0.6.2.dist-info/METADATA
mmv_im2im-0.6.2.dist-info/WHEEL
mmv_im2im-0.6.2.dist-info/entry_points.txt
mmv_im2im-0.6.2.dist-info/top_level.txt
mmv_im2im-0.6.2.dist-info/RECORD
