Metadata-Version: 2.4
Name: mmv_im2im
Version: 0.6.2
Summary: A python package for deep learning based image to image transformation
Author-email: Jianxu Chen <jianxuchen.ai@gmail.com>
License-Expression: MIT
Project-URL: Homepage, https://github.com/MMV-Lab/mmv_im2im
Keywords: deep learning,microscopy image analysis,biomedical image analysis
Classifier: Development Status :: 3 - Alpha
Classifier: Intended Audience :: Developers
Classifier: Natural Language :: English
Classifier: Programming Language :: Python :: 3.10
Classifier: Programming Language :: Python :: 3.11
Requires-Python: >=3.10
License-File: LICENSE
Requires-Dist: lightning>=2.5.2
Requires-Dist: torch>=2.6.0
Requires-Dist: monai>=1.5.0
Requires-Dist: bioio
Requires-Dist: pandas
Requires-Dist: scikit-image
Requires-Dist: protobuf
Requires-Dist: pyrallis
Requires-Dist: scikit-learn
Requires-Dist: tensorboard
Requires-Dist: numba
Requires-Dist: numpy
Requires-Dist: pydantic
Requires-Dist: fastapi
Requires-Dist: uvicorn
Requires-Dist: botocore
Requires-Dist: bioio-ome-tiff
Requires-Dist: bioio-ome-zarr
Requires-Dist: pydantic-zarr
Requires-Dist: bioio-tifffile
Requires-Dist: bioio-lif
Requires-Dist: ngff-zarr
Requires-Dist: tifffile
Requires-Dist: ome-types
Requires-Dist: imageio
Requires-Dist: zarr
Provides-Extra: advanced
Requires-Dist: tensorboard; extra == "advanced"
Provides-Extra: paper
Requires-Dist: quilt3; extra == "paper"
Requires-Dist: pooch; extra == "paper"
Requires-Dist: matplotlib>=3.10.5; extra == "paper"
Requires-Dist: notebook; extra == "paper"
Provides-Extra: image-io
Provides-Extra: dev
Requires-Dist: pytest-runner>=5.2; extra == "dev"
Requires-Dist: black>=19.10b0; extra == "dev"
Requires-Dist: codecov>=2.1.4; extra == "dev"
Requires-Dist: flake8>=3.8.3; extra == "dev"
Requires-Dist: flake8-debugger>=3.2.1; extra == "dev"
Requires-Dist: pytest>=5.4.3; extra == "dev"
Requires-Dist: pytest-cov>=2.9.0; extra == "dev"
Requires-Dist: pytest-raises>=0.11; extra == "dev"
Requires-Dist: scipy>=1.10.0; extra == "dev"
Requires-Dist: numpy; extra == "dev"
Requires-Dist: bump2version>=1.0.1; extra == "dev"
Requires-Dist: coverage>=5.1; extra == "dev"
Requires-Dist: ipython>=7.15.0; extra == "dev"
Requires-Dist: m2r2>=0.2.7; extra == "dev"
Requires-Dist: Sphinx>=3.4.3; extra == "dev"
Requires-Dist: sphinx_rtd_theme>=0.5.1; extra == "dev"
Requires-Dist: tox>=3.15.2; extra == "dev"
Requires-Dist: twine>=3.1.1; extra == "dev"
Requires-Dist: wheel>=0.34.2; extra == "dev"
Provides-Extra: test
Requires-Dist: black>=19.10b0; extra == "test"
Requires-Dist: codecov>=2.1.4; extra == "test"
Requires-Dist: flake8>=3.8.3; extra == "test"
Requires-Dist: flake8-debugger>=3.2.1; extra == "test"
Requires-Dist: pytest>=5.4.3; extra == "test"
Requires-Dist: pytest-cov>=2.9.0; extra == "test"
Requires-Dist: pytest-raises>=0.11; extra == "test"
Requires-Dist: numpy; extra == "test"
Provides-Extra: data-requirements
Requires-Dist: quilt3; extra == "data-requirements"
Requires-Dist: pooch; extra == "data-requirements"
Requires-Dist: matplotlib>=3.10.5; extra == "data-requirements"
Requires-Dist: notebook; extra == "data-requirements"
Provides-Extra: logger-requirements
Requires-Dist: tensorboard; extra == "logger-requirements"
Provides-Extra: all
Requires-Dist: mmv_im2im[advanced]; extra == "all"
Requires-Dist: mmv_im2im[paper]; extra == "all"
Requires-Dist: mmv_im2im[image-io]; extra == "all"
Requires-Dist: mmv_im2im[dev]; extra == "all"
Requires-Dist: mmv_im2im[test]; extra == "all"
Requires-Dist: mmv_im2im[data_requirements]; extra == "all"
Requires-Dist: mmv_im2im[logger_requirements]; extra == "all"
Provides-Extra: dynamic
Requires-Dist: optional-dependencies; extra == "dynamic"
Dynamic: license-file
